valtiopy/__init__.py
valtiopy/args.py
valtiopy/config.py
valtiopy/curate.py
valtiopy/metadata.py
valtiopy/plot.py
valtiopy/regex.py
valtiopy/rq/intros.rq
valtiopy/sample.py
valtiopy/utils.py
valtiopy-0.0.3.dist-info/LICENSE
valtiopy-0.0.3.dist-info/METADATA
valtiopy-0.0.3.dist-info/WHEEL
valtiopy-0.0.3.dist-info/RECORD
