Metadata-Version: 2.1
Name: valtiopy
Version: 0.0.3
Summary: Work with the Valtiopaivat Corpus.
Home-page: https://github.com/swerik-project/valtiopy
License: MIT
Author: bobborges
Requires-Python: >=3.7,<4.0
Classifier: License :: OSI Approved :: MIT License
Classifier: Programming Language :: Python :: 3
Classifier: Programming Language :: Python :: 3.7
Classifier: Programming Language :: Python :: 3.8
Classifier: Programming Language :: Python :: 3.9
Classifier: Programming Language :: Python :: 3.10
Classifier: Programming Language :: Python :: 3.11
Classifier: Programming Language :: Python :: 3.12
Classifier: Programming Language :: Python :: 3.13
Requires-Dist: pyriksdagen
Project-URL: Repository, https://github.com/swerik-project/valtiopy
